[
  {
    "coin": "Pepe420Moon",
    "score": 11.94875,
    "buy_price": 0.0153,
    "sell_price": 0.0204,
    "profit": 0.0051,
    "timestamp": 1753071091.5230072
  },
  {
    "coin": "Pepe420Moon",
    "score": 11.75575,
    "buy_price": 0.0159,
    "sell_price": 0.0343,
    "profit": 0.0184,
    "timestamp": 1753071091.5230694
  },
  {
    "coin": "Pepe420Moon",
    "score": 10.81725,
    "buy_price": 0.0169,
    "sell_price": 0.047,
    "profit": 0.0301,
    "timestamp": 1753071091.523114
  },
  {
    "coin": "Pepe420Moon",
    "score": 11.840250000000001,
    "buy_price": 0.0067,
    "sell_price": 0.0092,
    "profit": 0.0025,
    "timestamp": 1753071091.5231702
  },
  {
    "coin": "Pepe420Moon",
    "score": 12.362499999999999,
    "buy_price": 0.0195,
    "sell_price": 0.0386,
    "profit": 0.0191,
    "timestamp": 1753071098.9419565
  },
  {
    "coin": "Pepe420Moon",
    "score": 11.342500000000001,
    "buy_price": 0.0099,
    "sell_price": 0.0152,
    "profit": 0.0053,
    "timestamp": 1753071098.9420762
  },
  {
    "coin": "Pepe420Moon",
    "score": 10.266,
    "buy_price": 0.0188,
    "sell_price": 0.0561,
    "profit": 0.0373,
    "timestamp": 1753071100.7812042
  },
  {
    "coin": "Pepe420Moon",
    "score": 10.012500000000001,
    "buy_price": 0.0053,
    "sell_price": 0.0043,
    "profit": -0.001,
    "timestamp": 1753071100.7813427
  },
  {
    "coin": "Pepe420Moon",
    "score": 11.78075,
    "buy_price": 0.0178,
    "sell_price": 0.0459,
    "profit": 0.0281,
    "timestamp": 1753071100.7814186
  },
  {
    "coin": "Pepe420Moon",
    "score": 12.722999999999999,
    "buy_price": 0.0109,
    "sell_price": 0.0215,
    "profit": 0.0106,
    "timestamp": 1753071100.7814922
  },
  {
    "coin": "Pepe420Moon",
    "score": 10.155750000000001,
    "buy_price": 0.011,
    "sell_price": 0.0315,
    "profit": 0.0205,
    "timestamp": 1753071101.5218227
  },
  {
    "coin": "Pepe420Moon",
    "score": 10.207500000000001,
    "buy_price": 0.0194,
    "sell_price": 0.024,
    "profit": 0.0046,
    "timestamp": 1753071101.5221353
  },
  {
    "coin": "Pepe420Moon",
    "score": 12.18225,
    "buy_price": 0.014,
    "sell_price": 0.0153,
    "profit": 0.0013,
    "timestamp": 1753071102.4835062
  },
  {
    "coin": "Pepe420Moon",
    "score": 11.32475,
    "buy_price": 0.0056,
    "sell_price": 0.0135,
    "profit": 0.0079,
    "timestamp": 1753071103.090444
  },
  {
    "coin": "Pepe420Moon",
    "score": 10.77975,
    "buy_price": 0.0063,
    "sell_price": 0.011,
    "profit": 0.0047,
    "timestamp": 1753071103.0904703
  },
  {
    "coin": "Pepe420Moon",
    "score": 10.811000000000002,
    "buy_price": 0.0113,
    "sell_price": 0.0182,
    "profit": 0.0069,
    "timestamp": 1753071103.9893167
  },
  {
    "coin": "Pepe420Moon",
    "score": 10.886999999999999,
    "buy_price": 0.0164,
    "sell_price": 0.0106,
    "profit": -0.0058,
    "timestamp": 1753071106.7535744
  },
  {
    "coin": "Pepe420Moon",
    "score": 11.014999999999999,
    "buy_price": 0.0178,
    "sell_price": 0.0424,
    "profit": 0.0246,
    "timestamp": 1753071106.75367
  },
  {
    "coin": "Pepe420Moon",
    "score": 11.65275,
    "buy_price": 0.0165,
    "sell_price": 0.0117,
    "profit": -0.0048,
    "timestamp": 1753071106.75371
  },
  {
    "coin": "Pepe420Moon",
    "score": 9.9195,
    "buy_price": 0.0061,
    "sell_price": 0.013,
    "profit": 0.0069,
    "timestamp": 1753071106.7538204
  },
  {
    "coin": "Pepe420Moon",
    "score": 12.01,
    "buy_price": 0.0099,
    "sell_price": 0.0242,
    "profit": 0.0143,
    "timestamp": 1753071328.8993,
    "datetime": "2025-07-21 00:15:28"
  },
  {
    "coin": "Pepe420Moon",
    "score": 10.8,
    "buy_price": 0.0165,
    "sell_price": 0.0349,
    "profit": 0.0184,
    "timestamp": 1753071328.8993795,
    "datetime": "2025-07-21 00:15:28"
  },
  {
    "coin": "Pepe420Moon",
    "score": 10.67,
    "buy_price": 0.0159,
    "sell_price": 0.0347,
    "profit": 0.0188,
    "timestamp": 1753071328.8994455,
    "datetime": "2025-07-21 00:15:28"
  },
  {
    "coin": "Pepe420Moon",
    "score": 11.93,
    "buy_price": 0.0057,
    "sell_price": 0.0114,
    "profit": 0.0057,
    "timestamp": 1753071328.8995197,
    "datetime": "2025-07-21 00:15:28"
  },
  {
    "coin": "Pepe420Moon",
    "score": 10.57,
    "buy_price": 0.016,
    "sell_price": 0.018,
    "profit": 0.002,
    "timestamp": 1753071328.8995655,
    "datetime": "2025-07-21 00:15:28"
  },
  {
    "coin": "Pepe420Moon",
    "score": 10.87,
    "buy_price": 0.0165,
    "sell_price": 0.0165,
    "profit": 0.0,
    "timestamp": 1753071597.328657,
    "datetime": "2025-07-21 00:19:57"
  },
  {
    "coin": "Pepe420Moon",
    "score": 10.74,
    "buy_price": 0.0188,
    "sell_price": 0.0527,
    "profit": 0.0339,
    "timestamp": 1753071597.3288412,
    "datetime": "2025-07-21 00:19:57"
  }
]